{
    "PLD":
    [
        "Rage of Halone",
        "Sheltron",
        "Spirits Within"
    ],

    "WAR":
    [
        "Inner Beast",
        "Steel Cyclone",
        "Berserk",
        "Raw Intuition"
    ],

    "DRK":
    [
        "Flood of Darkness",
        "Edge of Darkness"
    ],

    "GNB":
    [
        "Danger Zone",
        "Heart of Stone"
    ],

    "WHM":
    [
        "Stone",
        "Aero",
        "Stone II",
        "Stone III",
        "Aero II",
        "Stone IV",
        "Glare",
        "Holy"
    ],

    "SCH":
    [
        "Bio",
        "Ruin",
        "Broil",
        "Bio II",
        "Broil II",
        "Broil III",
        "Art of War"
    ],

    "AST":
    [
        "Combust",
        "Malefic",
        "Malefic II",
        "Combust II",
        "Malefic III",
        "Malefic IV",
        "Gravity"
    ],

    "SGE":
    [
        "Physis",
        "Dosis",
        "Dosis II"
    ],

    "MNK":
    [
        "Steel Peak",
        "Howling Fist",
        "Arm of the Destroyer",
        "Flint Strike",
        "Tornado Kick"
    ],

    "DRG":
    [
        "Jump",
        "Full Thrust",
        "Chaos Thrust"
    ],

    "NIN":
    [
        "Assassinate"
    ],

    "SAM":
    [

    ],

    "BRD":
    [
        "Venomous Bite",
        "Windbite",
        "Straight Shot",
        "Heavy Shot",
        "Quick Knock"
    ],

    "MCH":
    [
        "Split Shot",
        "Slug Shot",
        "Clean Shot",
        "Hot Shot",
        "Rook Autoturret",
        "Spread Shot"
    ],

    "BLM":
    [
        "Thunder",
        "Thunder II",
        "Fire II",
        "Blizzard II"
    ],

    "SMN":
    [
        "Ruin",
        "Summon Ruby",
        "Summon Topaz",
        "Summon Emerald",
        "Ruin II",
        "Aethercharge",
        "Dreadwyrm Trance",
        "Outburst",
        "Summon Ifrit",
        "Summon Titan",
        "Summon Garuda"
    ],

    "RDM":
    [
        "Jolt",
        "Scatter",
        "Verthunder",
        "Veraero"
    ]
}
